[
  {
    "author": "ShadyTiger",
    "link_thumb": "https://live.staticflickr.com/65535/51674880719_e20ea4494b_o.gif",
    "link_bin": "https://github.com/lmbstudiocontact/mb4_48/raw/main/19256.bin",
    "id_bin": "19256",
    "list_language": [],
    "array_tags": [
      "date",
      "digital",
      "distance",
      "battery",
      "steps"
    ],
    "list_album": [
      {
        "id_album": "-1956005621",
        "link_thumb": "https://live.staticflickr.com/65535/51674880719_e20ea4494b_o.gif",
        "title": "None_2"
      }
    ]
  },
  {
    "author": "Vananh89",
    "link_thumb": "https://live.staticflickr.com/65535/51671944271_d37e369fd6_o.gif",
    "link_bin": "https://github.com/lmbstudiocontact/mb4_66/raw/main/437.bin",
    "id_bin": "437",
    "list_language": [],
    "array_tags": [
      "heart"
    ],
    "list_album": [
      {
        "id_album": "2374546",
        "link_thumb": "https://live.staticflickr.com/65535/51671944271_d37e369fd6_o.gif",
        "title": "Love"
      }
    ]
  },
  {
    "author": "KurisuWaifu",
    "link_thumb": "https://live.staticflickr.com/65535/51675109895_c77ba471f5_o.gif",
    "link_bin": "https://github.com/lmbstudiocontact/mb4_48/raw/main/19483.bin",
    "id_bin": "19483",
    "list_language": [],
    "array_tags": [
      "date",
      "battery",
      "steps",
      "anime"
    ],
    "list_album": [
      {
        "id_album": "-1956005621",
        "link_thumb": "https://live.staticflickr.com/65535/51675109895_c77ba471f5_o.gif",
        "title": "None_2"
      }
    ]
  },
  {
    "author": "DJACIR",
    "link_thumb": "https://live.staticflickr.com/65535/51674675053_6ac5234b15_o.gif",
    "link_bin": "https://github.com/lmbstudiocontact/mb4_49/raw/main/20818.bin",
    "id_bin": "20818",
    "list_language": [],
    "array_tags": [
      "date",
      "analog",
      "seconds",
      "floors",
      "heartrate",
      "calories",
      "steps"
    ],
    "list_album": [
      {
        "id_album": "-1956005621",
        "link_thumb": "https://live.staticflickr.com/65535/51674675053_6ac5234b15_o.gif",
        "title": "None_2"
      }
    ]
  },
  {
    "author": "None",
    "link_thumb": "https://live.staticflickr.com/65535/51675132189_bd8f3f6502_o.gif",
    "link_bin": "https://github.com/lmbstudiocontact/mb4_49/raw/main/21050.bin",
    "id_bin": "21050",
    "list_language": [],
    "array_tags": [],
    "list_album": [
      {
        "id_album": "2433880",
        "link_thumb": "https://live.staticflickr.com/65535/51675132189_bd8f3f6502_o.gif",
        "title": "None"
      }
    ]
  },
  {
    "author": "aishbi",
    "link_thumb": "https://live.staticflickr.com/65535/51673654852_17be4cd71d_o.gif",
    "link_bin": "https://github.com/lmbstudiocontact/mb4_49/raw/main/21026.bin",
    "id_bin": "21026",
    "list_language": [],
    "array_tags": [
      "digital",
      "date",
      "floors",
      "distance",
      "heartrate",
      "calories",
      "battery",
      "steps"
    ],
    "list_album": [
      {
        "id_album": "2433880",
        "link_thumb": "https://live.staticflickr.com/65535/51673654852_17be4cd71d_o.gif",
        "title": "None"
      }
    ]
  },
  {
    "author": "꧁༺₦Ї₦ℑ₳༻꧂",
    "link_thumb": "https://live.staticflickr.com/65535/51674992140_c89278859b_o.gif",
    "link_bin": "https://github.com/lmbstudiocontact/mb4_16/raw/main/16955.bin",
    "id_bin": "16955",
    "list_language": [],
    "array_tags": [
      "date"
    ],
    "list_album": [
      {
        "id_album": "-1956005621",
        "link_thumb": "https://live.staticflickr.com/65535/51674992140_c89278859b_o.gif",
        "title": "None_2"
      }
    ]
  },
  {
    "author": "Artark",
    "link_thumb": "https://live.staticflickr.com/65535/51672314359_06b38577ed_o.gif",
    "link_bin": "https://github.com/lmbstudiocontact/mb4_21/raw/main/18292.bin",
    "id_bin": "18292",
    "list_language": [],
    "array_tags": [
      "digital",
      "battery",
      "steps"
    ],
    "list_album": [
      {
        "id_album": "2433880",
        "link_thumb": "https://live.staticflickr.com/65535/51672314359_06b38577ed_o.gif",
        "title": "None"
      }
    ]
  },
  {
    "author": "Bacer",
    "link_thumb": "https://live.staticflickr.com/65535/51675017755_3895c65c6c_o.gif",
    "link_bin": "https://github.com/lmbstudiocontact/mb4_16/raw/main/18905.bin",
    "id_bin": "18905",
    "list_language": [],
    "array_tags": [
      "digital",
      "date",
      "russian",
      "nike",
      "battery"
    ],
    "list_album": [
      {
        "id_album": "-1956005621",
        "link_thumb": "https://live.staticflickr.com/65535/51675017755_3895c65c6c_o.gif",
        "title": "None_2"
      }
    ]
  },
  {
    "author": "shymik",
    "link_thumb": "https://live.staticflickr.com/65535/51674992290_034ac86070_o.gif",
    "link_bin": "https://github.com/lmbstudiocontact/mb4_16/raw/main/16958.bin",
    "id_bin": "16958",
    "list_language": [],
    "array_tags": [
      "digital",
      "date",
      "distance",
      "heartrate",
      "battery",
      "steps"
    ],
    "list_album": [
      {
        "id_album": "-1956005621",
        "link_thumb": "https://live.staticflickr.com/65535/51674992290_034ac86070_o.gif",
        "title": "None_2"
      }
    ]
  },
  {
    "author": "ddkstw",
    "link_thumb": "https://live.staticflickr.com/65535/51672166428_95795d9c01_o.gif",
    "link_bin": "https://github.com/lmbstudiocontact/mb4_66/raw/main/4228.bin",
    "id_bin": "4228",
    "list_language": [],
    "array_tags": [
      "english",
      "indonesia"
    ],
    "list_album": [
      {
        "id_album": "65078219",
        "link_thumb": "https://live.staticflickr.com/65535/51672166428_95795d9c01_o.gif",
        "title": "Chibi"
      }
    ]
  },
  {
    "author": "LMB Studio",
    "link_thumb": "https://live.staticflickr.com/65535/51673875176_46ac5c778c_o.gif",
    "link_bin": "https://github.com/lmbstudiocontact/mb4_38/raw/main/Cute Art_L4_-622361123.bin",
    "id_bin": "Cute Art_L4_-622361123",
    "list_language": [
      {
        "author": "LMB Studio",
        "link_thumb": "https://live.staticflickr.com/65535/51673070942_b8dea46e51_o.gif",
        "link_bin": "https://github.com/lmbstudiocontact/mb4_38/raw/main/Cute Art_L4_-622361123_English.bin",
        "name_language": "English",
        "id_bin_language": "Cute Art_L4_-622361123_English"
      },
      {
        "author": "LMB Studio",
        "link_thumb": "https://live.staticflickr.com/65535/51673071037_cd7e8094c2_o.gif",
        "link_bin": "https://github.com/lmbstudiocontact/mb4_38/raw/main/Cute Art_L4_-622361123_Portuguese.bin",
        "name_language": "Portuguese",
        "id_bin_language": "Cute Art_L4_-622361123_Portuguese"
      },
      {
        "author": "LMB Studio",
        "link_thumb": "https://live.staticflickr.com/65535/51673071147_4a97d8d89d_o.gif",
        "link_bin": "https://github.com/lmbstudiocontact/mb4_38/raw/main/Cute Art_L4_-622361123_Russian.bin",
        "name_language": "Russian",
        "id_bin_language": "Cute Art_L4_-622361123_Russian"
      },
      {
        "author": "LMB Studio",
        "link_thumb": "https://live.staticflickr.com/65535/51674746625_13d7a46d4c_o.gif",
        "link_bin": "https://github.com/lmbstudiocontact/mb4_38/raw/main/Cute Art_L4_-622361123_Spanish.bin",
        "name_language": "Spanish",
        "id_bin_language": "Cute Art_L4_-622361123_Spanish"
      }
    ],
    "array_tags": [
      "lmbstudio"
    ],
    "list_album": [
      {
        "id_album": "-629963487",
        "link_thumb": "https://live.staticflickr.com/65535/51673875176_46ac5c778c_o.gif",
        "title": "Cute Art_L4"
      }
    ]
  },
  {
    "author": "Anquietas",
    "link_thumb": "https://live.staticflickr.com/65535/51675124914_8b5c1120af_o.gif",
    "link_bin": "https://github.com/lmbstudiocontact/mb4_49/raw/main/20988.bin",
    "id_bin": "20988",
    "list_language": [],
    "array_tags": [],
    "list_album": [
      {
        "id_album": "2433880",
        "link_thumb": "https://live.staticflickr.com/65535/51675124914_8b5c1120af_o.gif",
        "title": "None"
      }
    ]
  },
  {
    "author": "zuggi1985",
    "link_thumb": "https://live.staticflickr.com/65535/51674437493_3bb8e8c7e5_o.gif",
    "link_bin": "https://github.com/lmbstudiocontact/mb4_16/raw/main/19180.bin",
    "id_bin": "19180",
    "list_language": [],
    "array_tags": [
      "digital"
    ],
    "list_album": [
      {
        "id_album": "-1956005621",
        "link_thumb": "https://live.staticflickr.com/65535/51674437493_3bb8e8c7e5_o.gif",
        "title": "None_2"
      }
    ]
  },
  {
    "author": "Saitama",
    "link_thumb": "https://live.staticflickr.com/65535/51672942185_43b78ecf34_o.gif",
    "link_bin": "https://github.com/lmbstudiocontact/mb4_66/raw/main/550.bin",
    "id_bin": "550",
    "list_language": [],
    "array_tags": [
      "date",
      "battery",
      "steps"
    ],
    "list_album": [
      {
        "id_album": "63410260",
        "link_thumb": "https://live.staticflickr.com/65535/51672942185_43b78ecf34_o.gif",
        "title": "Anime"
      }
    ]
  },
  {
    "author": "LMB Studio",
    "link_thumb": "https://live.staticflickr.com/65535/51675705106_82d56c6ff8_o.gif",
    "link_bin": "https://github.com/lmbstudiocontact/mb4_19/raw/main/Dragon Art_L3_-145415856.bin",
    "id_bin": "Dragon Art_L3_-145415856",
    "list_language": [
      {
        "author": "LMB Studio",
        "link_thumb": "https://live.staticflickr.com/65535/51675950168_367357d462_o.gif",
        "link_bin": "https://github.com/lmbstudiocontact/mb4_19/raw/main/Dragon Art_L3_-145415856_English.bin",
        "name_language": "English",
        "id_bin_language": "Dragon Art_L3_-145415856_English"
      },
      {
        "author": "LMB Studio",
        "link_thumb": "https://live.staticflickr.com/65535/51675705321_e69c06cdb7_o.gif",
        "link_bin": "https://github.com/lmbstudiocontact/mb4_19/raw/main/Dragon Art_L3_-145415856_Portuguese.bin",
        "name_language": "Portuguese",
        "id_bin_language": "Dragon Art_L3_-145415856_Portuguese"
      },
      {
        "author": "LMB Studio",
        "link_thumb": "https://live.staticflickr.com/65535/51676582655_bf177b4106_o.gif",
        "link_bin": "https://github.com/lmbstudiocontact/mb4_19/raw/main/Dragon Art_L3_-145415856_Russian.bin",
        "name_language": "Russian",
        "id_bin_language": "Dragon Art_L3_-145415856_Russian"
      },
      {
        "author": "LMB Studio",
        "link_thumb": "https://live.staticflickr.com/65535/51675950643_a9e829355e_o.gif",
        "link_bin": "https://github.com/lmbstudiocontact/mb4_19/raw/main/Dragon Art_L3_-145415856_Spanish.bin",
        "name_language": "Spanish",
        "id_bin_language": "Dragon Art_L3_-145415856_Spanish"
      }
    ],
    "array_tags": [
      "lmbstudio"
    ],
    "list_album": [
      {
        "id_album": "2059014000",
        "link_thumb": "https://live.staticflickr.com/65535/51675705106_82d56c6ff8_o.gif",
        "title": "Dragon Art_L3"
      }
    ]
  },
  {
    "author": "LMB Studio",
    "link_thumb": "https://live.staticflickr.com/65535/51673072272_2191b2491b_o.gif",
    "link_bin": "https://github.com/lmbstudiocontact/mb4_38/raw/main/Cute Art_L4_-684165572.bin",
    "id_bin": "Cute Art_L4_-684165572",
    "list_language": [
      {
        "author": "LMB Studio",
        "link_thumb": "https://live.staticflickr.com/65535/51674546099_b392d23cd6_o.gif",
        "link_bin": "https://github.com/lmbstudiocontact/mb4_38/raw/main/Cute Art_L4_-684165572_English.bin",
        "name_language": "English",
        "id_bin_language": "Cute Art_L4_-684165572_English"
      },
      {
        "author": "LMB Studio",
        "link_thumb": "https://live.staticflickr.com/65535/51673072752_8d88076e4e_o.gif",
        "link_bin": "https://github.com/lmbstudiocontact/mb4_38/raw/main/Cute Art_L4_-684165572_Portuguese.bin",
        "name_language": "Portuguese",
        "id_bin_language": "Cute Art_L4_-684165572_Portuguese"
      },
      {
        "author": "LMB Studio",
        "link_thumb": "https://live.staticflickr.com/65535/51674748225_076bd56da5_o.gif",
        "link_bin": "https://github.com/lmbstudiocontact/mb4_38/raw/main/Cute Art_L4_-684165572_Russian.bin",
        "name_language": "Russian",
        "id_bin_language": "Cute Art_L4_-684165572_Russian"
      },
      {
        "author": "LMB Studio",
        "link_thumb": "https://live.staticflickr.com/65535/51674112648_d0a537366d_o.gif",
        "link_bin": "https://github.com/lmbstudiocontact/mb4_38/raw/main/Cute Art_L4_-684165572_Spanish.bin",
        "name_language": "Spanish",
        "id_bin_language": "Cute Art_L4_-684165572_Spanish"
      }
    ],
    "array_tags": [
      "lmbstudio"
    ],
    "list_album": [
      {
        "id_album": "-629963487",
        "link_thumb": "https://live.staticflickr.com/65535/51673072272_2191b2491b_o.gif",
        "title": "Cute Art_L4"
      }
    ]
  },
  {
    "author": "LMB Studio",
    "link_thumb": "https://live.staticflickr.com/65535/51673902741_1e01b89090_o.gif",
    "link_bin": "https://github.com/lmbstudiocontact/mb4_38/raw/main/Cute Art_L4_820347835.bin",
    "id_bin": "Cute Art_L4_820347835",
    "list_language": [
      {
        "author": "LMB Studio",
        "link_thumb": "https://live.staticflickr.com/65535/51674137423_ae98ba7cb1_o.gif",
        "link_bin": "https://github.com/lmbstudiocontact/mb4_38/raw/main/Cute Art_L4_820347835_English.bin",
        "name_language": "English",
        "id_bin_language": "Cute Art_L4_820347835_English"
      },
      {
        "author": "LMB Studio",
        "link_thumb": "https://live.staticflickr.com/65535/51673098402_80f4826952_o.gif",
        "link_bin": "https://github.com/lmbstudiocontact/mb4_38/raw/main/Cute Art_L4_820347835_Portuguese.bin",
        "name_language": "Portuguese",
        "id_bin_language": "Cute Art_L4_820347835_Portuguese"
      },
      {
        "author": "LMB Studio",
        "link_thumb": "https://live.staticflickr.com/65535/51674774295_d5a4f5d623_o.gif",
        "link_bin": "https://github.com/lmbstudiocontact/mb4_38/raw/main/Cute Art_L4_820347835_Russian.bin",
        "name_language": "Russian",
        "id_bin_language": "Cute Art_L4_820347835_Russian"
      },
      {
        "author": "LMB Studio",
        "link_thumb": "https://live.staticflickr.com/65535/51673903526_4e9c30a9e3_o.gif",
        "link_bin": "https://github.com/lmbstudiocontact/mb4_38/raw/main/Cute Art_L4_820347835_Spanish.bin",
        "name_language": "Spanish",
        "id_bin_language": "Cute Art_L4_820347835_Spanish"
      }
    ],
    "array_tags": [
      "lmbstudio"
    ],
    "list_album": [
      {
        "id_album": "-629963487",
        "link_thumb": "https://live.staticflickr.com/65535/51673902741_1e01b89090_o.gif",
        "title": "Cute Art_L4"
      }
    ]
  },
  {
    "author": "Unknown Epic",
    "link_thumb": "https://live.staticflickr.com/65535/51674349898_816962cba3_o.gif",
    "link_bin": "https://github.com/lmbstudiocontact/mb4_16/raw/main/16883.bin",
    "id_bin": "16883",
    "list_language": [],
    "array_tags": [
      "fireflames"
    ],
    "list_album": [
      {
        "id_album": "-1956005621",
        "link_thumb": "https://live.staticflickr.com/65535/51674349898_816962cba3_o.gif",
        "title": "None_2"
      }
    ]
  },
  {
    "author": "tomlucena",
    "link_thumb": "https://live.staticflickr.com/65535/51675003800_9b73ca472f_o.gif",
    "link_bin": "https://github.com/lmbstudiocontact/mb4_16/raw/main/18605.bin",
    "id_bin": "18605",
    "list_language": [],
    "array_tags": [
      "dc"
    ],
    "list_album": [
      {
        "id_album": "-1956005621",
        "link_thumb": "https://live.staticflickr.com/65535/51675003800_9b73ca472f_o.gif",
        "title": "None_2"
      }
    ]
  },
  {
    "author": "MADSL",
    "link_thumb": "https://live.staticflickr.com/65535/51674695479_99c82f9500_o.gif",
    "link_bin": "https://github.com/lmbstudiocontact/mb4_16/raw/main/16133.bin",
    "id_bin": "16133",
    "list_language": [],
    "array_tags": [
      "red",
      "xiaomi",
      "mi"
    ],
    "list_album": [
      {
        "id_album": "2433880",
        "link_thumb": "https://live.staticflickr.com/65535/51674695479_99c82f9500_o.gif",
        "title": "None"
      }
    ]
  },
  {
    "author": "CzAlien",
    "link_thumb": "https://live.staticflickr.com/65535/51674929160_998b490bde_o.gif",
    "link_bin": "https://github.com/lmbstudiocontact/mb4_16/raw/main/16420.bin",
    "id_bin": "16420",
    "list_language": [],
    "array_tags": [
      "digital",
      "date",
      "distance",
      "cz",
      "calories",
      "battery",
      "steps"
    ],
    "list_album": [
      {
        "id_album": "-1956005621",
        "link_thumb": "https://live.staticflickr.com/65535/51674929160_998b490bde_o.gif",
        "title": "None_2"
      }
    ]
  },
  {
    "author": "Agus_cord2",
    "link_thumb": "https://live.staticflickr.com/65535/51670591402_d357b735f1_o.gif",
    "link_bin": "https://github.com/lmbstudiocontact/mb4_17/raw/main/1249.bin",
    "id_bin": "1249",
    "list_language": [],
    "array_tags": [
      "digital"
    ],
    "list_album": [
      {
        "id_album": "898853208",
        "link_thumb": "https://live.staticflickr.com/65535/51670591402_d357b735f1_o.gif",
        "title": "Flowers"
      }
    ]
  },
  {
    "author": "LMB Studio",
    "link_thumb": "https://live.staticflickr.com/65535/51675949218_e5dbd429e7_o.gif",
    "link_bin": "https://github.com/lmbstudiocontact/mb4_19/raw/main/Dragon Art_L3_-145384018.bin",
    "id_bin": "Dragon Art_L3_-145384018",
    "list_language": [
      {
        "author": "LMB Studio",
        "link_thumb": "https://live.staticflickr.com/65535/51674903362_d5209765ee_o.gif",
        "link_bin": "https://github.com/lmbstudiocontact/mb4_19/raw/main/Dragon Art_L3_-145384018_English.bin",
        "name_language": "English",
        "id_bin_language": "Dragon Art_L3_-145384018_English"
      },
      {
        "author": "LMB Studio",
        "link_thumb": "https://live.staticflickr.com/65535/51675949498_3a2a3bb033_o.gif",
        "link_bin": "https://github.com/lmbstudiocontact/mb4_19/raw/main/Dragon Art_L3_-145384018_Portuguese.bin",
        "name_language": "Portuguese",
        "id_bin_language": "Dragon Art_L3_-145384018_Portuguese"
      },
      {
        "author": "LMB Studio",
        "link_thumb": "https://live.staticflickr.com/65535/51676581745_00359be128_o.gif",
        "link_bin": "https://github.com/lmbstudiocontact/mb4_19/raw/main/Dragon Art_L3_-145384018_Russian.bin",
        "name_language": "Russian",
        "id_bin_language": "Dragon Art_L3_-145384018_Russian"
      },
      {
        "author": "LMB Studio",
        "link_thumb": "https://live.staticflickr.com/65535/51675705006_5cae1d228c_o.gif",
        "link_bin": "https://github.com/lmbstudiocontact/mb4_19/raw/main/Dragon Art_L3_-145384018_Spanish.bin",
        "name_language": "Spanish",
        "id_bin_language": "Dragon Art_L3_-145384018_Spanish"
      }
    ],
    "array_tags": [
      "lmbstudio"
    ],
    "list_album": [
      {
        "id_album": "2059014000",
        "link_thumb": "https://live.staticflickr.com/65535/51675949218_e5dbd429e7_o.gif",
        "title": "Dragon Art_L3"
      }
    ]
  },
  {
    "author": "Beradam",
    "link_thumb": "https://live.staticflickr.com/65535/51670716177_9e00270ecd_o.gif",
    "link_bin": "https://github.com/lmbstudiocontact/mb4_1/raw/main/17245.bin",
    "id_bin": "17245",
    "list_language": [],
    "array_tags": [
      "digital",
      "date",
      "battery",
      "steps"
    ],
    "list_album": [
      {
        "id_album": "2433880",
        "link_thumb": "https://live.staticflickr.com/65535/51670716177_9e00270ecd_o.gif",
        "title": "None"
      }
    ]
  },
  {
    "author": "HAJAH",
    "link_thumb": "https://live.staticflickr.com/65535/51673244752_34b3c56e9d_o.gif",
    "link_bin": "https://github.com/lmbstudiocontact/mb4_16/raw/main/16319.bin",
    "id_bin": "16319",
    "list_language": [],
    "array_tags": [
      "animado",
      "azul"
    ],
    "list_album": [
      {
        "id_album": "-1956005621",
        "link_thumb": "https://live.staticflickr.com/65535/51673244752_34b3c56e9d_o.gif",
        "title": "None_2"
      }
    ]
  },
  {
    "author": "ViniKuster",
    "link_thumb": "https://live.staticflickr.com/65535/51671507901_815103fea4_o.gif",
    "link_bin": "https://github.com/lmbstudiocontact/mb4_1/raw/main/17129.bin",
    "id_bin": "17129",
    "list_language": [],
    "array_tags": [
      "miband5",
      "miband",
      "miband4"
    ],
    "list_album": [
      {
        "id_album": "2433880",
        "link_thumb": "https://live.staticflickr.com/65535/51671507901_815103fea4_o.gif",
        "title": "None"
      }
    ]
  },
  {
    "author": "plut",
    "link_thumb": "https://live.staticflickr.com/65535/51674274618_26056b9ed8_o.gif",
    "link_bin": "https://github.com/lmbstudiocontact/mb4_16/raw/main/16210.bin",
    "id_bin": "16210",
    "list_language": [],
    "array_tags": [
      "analog",
      "miband",
      "battery",
      "steps"
    ],
    "list_album": [
      {
        "id_album": "2433880",
        "link_thumb": "https://live.staticflickr.com/65535/51674274618_26056b9ed8_o.gif",
        "title": "None"
      }
    ]
  },
  {
    "author": "timjones",
    "link_thumb": "https://live.staticflickr.com/65535/51672223544_abe3020f9e_o.gif",
    "link_bin": "https://github.com/lmbstudiocontact/mb4_1/raw/main/17497.bin",
    "id_bin": "17497",
    "list_language": [],
    "array_tags": [
      "digital",
      "date",
      "seconds",
      "distance",
      "battery"
    ],
    "list_album": [
      {
        "id_album": "2433880",
        "link_thumb": "https://live.staticflickr.com/65535/51672223544_abe3020f9e_o.gif",
        "title": "None"
      }
    ]
  },
  {
    "author": "soyyo",
    "link_thumb": "https://live.staticflickr.com/65535/51674948940_ff95e54059_o.gif",
    "link_bin": "https://github.com/lmbstudiocontact/mb4_16/raw/main/16609.bin",
    "id_bin": "16609",
    "list_language": [],
    "array_tags": [
      "digital",
      "date",
      "analog",
      "heartrate",
      "battery",
      "steps"
    ],
    "list_album": [
      {
        "id_album": "-1956005621",
        "link_thumb": "https://live.staticflickr.com/65535/51674948940_ff95e54059_o.gif",
        "title": "None_2"
      }
    ]
  },
  {
    "author": "kakheng1996",
    "link_thumb": "https://live.staticflickr.com/65535/51672493514_702e5990fc_o.gif",
    "link_bin": "https://github.com/lmbstudiocontact/mb4_6/raw/main/3119.bin",
    "id_bin": "3119",
    "list_language": [],
    "array_tags": [
      "digital",
      "date",
      "battery",
      "steps"
    ],
    "list_album": [
      {
        "id_album": "63410260",
        "link_thumb": "https://live.staticflickr.com/65535/51672493514_702e5990fc_o.gif",
        "title": "Anime"
      }
    ]
  },
  {
    "author": "Alexoandros",
    "link_thumb": "https://live.staticflickr.com/65535/51671853668_3345d38a3c_o.gif",
    "link_bin": "https://github.com/lmbstudiocontact/mb4_21/raw/main/18081.bin",
    "id_bin": "18081",
    "list_language": [],
    "array_tags": [
      "digital",
      "date",
      "seconds",
      "battery",
      "steps"
    ],
    "list_album": [
      {
        "id_album": "2433880",
        "link_thumb": "https://live.staticflickr.com/65535/51671853668_3345d38a3c_o.gif",
        "title": "None"
      }
    ]
  },
  {
    "author": "None",
    "link_thumb": "https://live.staticflickr.com/65535/51675131509_bec520a3aa_o.gif",
    "link_bin": "https://github.com/lmbstudiocontact/mb4_49/raw/main/21048.bin",
    "id_bin": "21048",
    "list_language": [],
    "array_tags": [],
    "list_album": [
      {
        "id_album": "2433880",
        "link_thumb": "https://live.staticflickr.com/65535/51675131509_bec520a3aa_o.gif",
        "title": "None"
      }
    ]
  },
  {
    "author": "soyyo",
    "link_thumb": "https://live.staticflickr.com/65535/51674314828_c673615fc8_o.gif",
    "link_bin": "https://github.com/lmbstudiocontact/mb4_16/raw/main/16610.bin",
    "id_bin": "16610",
    "list_language": [],
    "array_tags": [
      "digital",
      "date",
      "analog",
      "heartrate",
      "battery",
      "steps"
    ],
    "list_album": [
      {
        "id_album": "-1956005621",
        "link_thumb": "https://live.staticflickr.com/65535/51674314828_c673615fc8_o.gif",
        "title": "None_2"
      }
    ]
  },
  {
    "author": "pacow",
    "link_thumb": "https://live.staticflickr.com/65535/51674209691_347091d7a3_o.gif",
    "link_bin": "https://github.com/lmbstudiocontact/mb4_48/raw/main/19248.bin",
    "id_bin": "19248",
    "list_language": [],
    "array_tags": [
      "digital",
      "date",
      "distance",
      "heartrate",
      "pulse",
      "calories",
      "battery",
      "lcd",
      "steps"
    ],
    "list_album": [
      {
        "id_album": "-1956005621",
        "link_thumb": "https://live.staticflickr.com/65535/51674209691_347091d7a3_o.gif",
        "title": "None_2"
      }
    ]
  },
  {
    "author": "Sedative",
    "link_thumb": "https://live.staticflickr.com/65535/51674404113_c300983f8c_o.gif",
    "link_bin": "https://github.com/lmbstudiocontact/mb4_16/raw/main/19012.bin",
    "id_bin": "19012",
    "list_language": [],
    "array_tags": [
      "digital",
      "date",
      "heartrate",
      "battery",
      "steps"
    ],
    "list_album": [
      {
        "id_album": "-1956005621",
        "link_thumb": "https://live.staticflickr.com/65535/51674404113_c300983f8c_o.gif",
        "title": "None_2"
      }
    ]
  },
  {
    "author": "Subbota_kot",
    "link_thumb": "https://live.staticflickr.com/65535/51675293205_9af5ba10bf_o.gif",
    "link_bin": "https://github.com/lmbstudiocontact/mb4_49/raw/main/20717.bin",
    "id_bin": "20717",
    "list_language": [],
    "array_tags": [
      "digital",
      "date",
      "battery",
      "steps"
    ],
    "list_album": [
      {
        "id_album": "-1956005621",
        "link_thumb": "https://live.staticflickr.com/65535/51675293205_9af5ba10bf_o.gif",
        "title": "None_2"
      }
    ]
  },
  {
    "author": "[email protected]",
    "link_thumb": "https://live.staticflickr.com/65535/51673255172_35b2aed21c_o.gif",
    "link_bin": "https://github.com/lmbstudiocontact/mb4_16/raw/main/16423.bin",
    "id_bin": "16423",
    "list_language": [],
    "array_tags": [
      "digital",
      "date",
      "days",
      "battery",
      "steps",
      "batman",
      "dc"
    ],
    "list_album": [
      {
        "id_album": "-1956005621",
        "link_thumb": "https://live.staticflickr.com/65535/51673255172_35b2aed21c_o.gif",
        "title": "None_2"
      }
    ]
  },
  {
    "author": "Sedative",
    "link_thumb": "https://live.staticflickr.com/65535/51674408913_d5d0286367_o.gif",
    "link_bin": "https://github.com/lmbstudiocontact/mb4_16/raw/main/19031.bin",
    "id_bin": "19031",
    "list_language": [],
    "array_tags": [
      "digital",
      "date",
      "distance",
      "calories",
      "battery",
      "steps"
    ],
    "list_album": [
      {
        "id_album": "-1956005621",
        "link_thumb": "https://live.staticflickr.com/65535/51674408913_d5d0286367_o.gif",
        "title": "None_2"
      }
    ]
  },
  {
    "author": "TinoCet",
    "link_thumb": "https://live.staticflickr.com/65535/51670706417_086cf8f37f_o.gif",
    "link_bin": "https://github.com/lmbstudiocontact/mb4_1/raw/main/17132.bin",
    "id_bin": "17132",
    "list_language": [],
    "array_tags": [
      "digital",
      "date",
      "analog",
      "seconds",
      "heartrate",
      "battery",
      "steps"
    ],
    "list_album": [
      {
        "id_album": "2433880",
        "link_thumb": "https://live.staticflickr.com/65535/51670706417_086cf8f37f_o.gif",
        "title": "None"
      }
    ]
  },
  {
    "author": "Duenti",
    "link_thumb": "https://live.staticflickr.com/65535/51672463765_b1ba76ee4b_o.gif",
    "link_bin": "https://github.com/lmbstudiocontact/mb4_1/raw/main/17930.bin",
    "id_bin": "17930",
    "list_language": [],
    "array_tags": [
      "digital",
      "date",
      "pokemon",
      "battery",
      "steps"
    ],
    "list_album": [
      {
        "id_album": "2433880",
        "link_thumb": "https://live.staticflickr.com/65535/51672463765_b1ba76ee4b_o.gif",
        "title": "None"
      }
    ]
  },
  {
    "author": "LluisQuilez",
    "link_thumb": "https://live.staticflickr.com/65535/51672275279_630c815697_o.gif",
    "link_bin": "https://github.com/lmbstudiocontact/mb4_1/raw/main/17948.bin",
    "id_bin": "17948",
    "list_language": [],
    "array_tags": [
      "digital",
      "date",
      "pulse",
      "steps"
    ],
    "list_album": [
      {
        "id_album": "2433880",
        "link_thumb": "https://live.staticflickr.com/65535/51672275279_630c815697_o.gif",
        "title": "None"
      }
    ]
  },
  {
    "author": "LMB Studio",
    "link_thumb": "https://live.staticflickr.com/65535/51674136178_3a203b8b2a_o.gif",
    "link_bin": "https://github.com/lmbstudiocontact/mb4_38/raw/main/Cute Art_L4_819661741.bin",
    "id_bin": "Cute Art_L4_819661741",
    "list_language": [
      {
        "author": "LMB Studio",
        "link_thumb": "https://live.staticflickr.com/65535/51674136333_624f5f5029_o.gif",
        "link_bin": "https://github.com/lmbstudiocontact/mb4_38/raw/main/Cute Art_L4_819661741_English.bin",
        "name_language": "English",
        "id_bin_language": "Cute Art_L4_819661741_English"
      },
      {
        "author": "LMB Studio",
        "link_thumb": "https://live.staticflickr.com/65535/51673097537_58f807fe1e_o.gif",
        "link_bin": "https://github.com/lmbstudiocontact/mb4_38/raw/main/Cute Art_L4_819661741_Portuguese.bin",
        "name_language": "Portuguese",
        "id_bin_language": "Cute Art_L4_819661741_Portuguese"
      },
      {
        "author": "LMB Studio",
        "link_thumb": "https://live.staticflickr.com/65535/51674773265_d2fd81ceeb_o.gif",
        "link_bin": "https://github.com/lmbstudiocontact/mb4_38/raw/main/Cute Art_L4_819661741_Russian.bin",
        "name_language": "Russian",
        "id_bin_language": "Cute Art_L4_819661741_Russian"
      },
      {
        "author": "LMB Studio",
        "link_thumb": "https://live.staticflickr.com/65535/51673097847_73283b3c9a_o.gif",
        "link_bin": "https://github.com/lmbstudiocontact/mb4_38/raw/main/Cute Art_L4_819661741_Spanish.bin",
        "name_language": "Spanish",
        "id_bin_language": "Cute Art_L4_819661741_Spanish"
      }
    ],
    "array_tags": [
      "lmbstudio"
    ],
    "list_album": [
      {
        "id_album": "-629963487",
        "link_thumb": "https://live.staticflickr.com/65535/51674136178_3a203b8b2a_o.gif",
        "title": "Cute Art_L4"
      }
    ]
  },
  {
    "author": "Bradrmiller18",
    "link_thumb": "https://live.staticflickr.com/65535/51674880429_401d7610b4_o.gif",
    "link_bin": "https://github.com/lmbstudiocontact/mb4_48/raw/main/19254.bin",
    "id_bin": "19254",
    "list_language": [],
    "array_tags": [
      "digital",
      "date",
      "heartrate",
      "battery",
      "steps"
    ],
    "list_album": [
      {
        "id_album": "-1956005621",
        "link_thumb": "https://live.staticflickr.com/65535/51674880429_401d7610b4_o.gif",
        "title": "None_2"
      }
    ]
  },
  {
    "author": "danilicious",
    "link_thumb": "https://live.staticflickr.com/65535/51674707379_471a5006ae_o.gif",
    "link_bin": "https://github.com/lmbstudiocontact/mb4_16/raw/main/16214.bin",
    "id_bin": "16214",
    "list_language": [],
    "array_tags": [
      "digital",
      "date",
      "distance",
      "heartrate",
      "calories",
      "battery",
      "steps"
    ],
    "list_album": [
      {
        "id_album": "2433880",
        "link_thumb": "https://live.staticflickr.com/65535/51674707379_471a5006ae_o.gif",
        "title": "None"
      }
    ]
  },
  {
    "author": "1imonad",
    "link_thumb": "https://live.staticflickr.com/65535/51671866478_5905c58db7_o.gif",
    "link_bin": "https://github.com/lmbstudiocontact/mb4_21/raw/main/18193.bin",
    "id_bin": "18193",
    "list_language": [],
    "array_tags": [],
    "list_album": [
      {
        "id_album": "2433880",
        "link_thumb": "https://live.staticflickr.com/65535/51671866478_5905c58db7_o.gif",
        "title": "None"
      }
    ]
  },
  {
    "author": "raxdata",
    "link_thumb": "https://live.staticflickr.com/65535/51670812452_96786786b4_o.gif",
    "link_bin": "https://github.com/lmbstudiocontact/mb4_21/raw/main/18088.bin",
    "id_bin": "18088",
    "list_language": [],
    "array_tags": [
      "digital",
      "date",
      "seconds",
      "heartrate",
      "weather",
      "battery",
      "steps"
    ],
    "list_album": [
      {
        "id_album": "2433880",
        "link_thumb": "https://live.staticflickr.com/65535/51670812452_96786786b4_o.gif",
        "title": "None"
      }
    ]
  },
  {
    "author": "LMB Studio",
    "link_thumb": "https://live.staticflickr.com/65535/51674745290_49cb7c6ac8_o.gif",
    "link_bin": "https://github.com/lmbstudiocontact/mb4_38/raw/main/Cute Art_L4_-622361122.bin",
    "id_bin": "Cute Art_L4_-622361122",
    "list_language": [
      {
        "author": "LMB Studio",
        "link_thumb": "https://live.staticflickr.com/65535/51674109893_a9841d74de_o.gif",
        "link_bin": "https://github.com/lmbstudiocontact/mb4_38/raw/main/Cute Art_L4_-622361122_English.bin",
        "name_language": "English",
        "id_bin_language": "Cute Art_L4_-622361122_English"
      },
      {
        "author": "LMB Studio",
        "link_thumb": "https://live.staticflickr.com/65535/51673070392_9e5e7bd33f_o.gif",
        "link_bin": "https://github.com/lmbstudiocontact/mb4_38/raw/main/Cute Art_L4_-622361122_Portuguese.bin",
        "name_language": "Portuguese",
        "id_bin_language": "Cute Art_L4_-622361122_Portuguese"
      },
      {
        "author": "LMB Studio",
        "link_thumb": "https://live.staticflickr.com/65535/51674110163_4e68eecca4_o.gif",
        "link_bin": "https://github.com/lmbstudiocontact/mb4_38/raw/main/Cute Art_L4_-622361122_Russian.bin",
        "name_language": "Russian",
        "id_bin_language": "Cute Art_L4_-622361122_Russian"
      },
      {
        "author": "LMB Studio",
        "link_thumb": "https://live.staticflickr.com/65535/51674745900_270bd27905_o.gif",
        "link_bin": "https://github.com/lmbstudiocontact/mb4_38/raw/main/Cute Art_L4_-622361122_Spanish.bin",
        "name_language": "Spanish",
        "id_bin_language": "Cute Art_L4_-622361122_Spanish"
      }
    ],
    "array_tags": [
      "lmbstudio"
    ],
    "list_album": [
      {
        "id_album": "-629963487",
        "link_thumb": "https://live.staticflickr.com/65535/51674745290_49cb7c6ac8_o.gif",
        "title": "Cute Art_L4"
      }
    ]
  },
  {
    "author": "WillowUser",
    "link_thumb": "https://live.staticflickr.com/65535/51674864554_e30e02661f_o.gif",
    "link_bin": "https://github.com/lmbstudiocontact/mb4_16/raw/main/19147.bin",
    "id_bin": "19147",
    "list_language": [],
    "array_tags": [
      "digital",
      "date",
      "heartrate",
      "battery",
      "steps"
    ],
    "list_album": [
      {
        "id_album": "-1956005621",
        "link_thumb": "https://live.staticflickr.com/65535/51674864554_e30e02661f_o.gif",
        "title": "None_2"
      }
    ]
  },
  {
    "author": "CzAlien",
    "link_thumb": "https://live.staticflickr.com/65535/51672428715_5b362ecd27_o.gif",
    "link_bin": "https://github.com/lmbstudiocontact/mb4_1/raw/main/17616.bin",
    "id_bin": "17616",
    "list_language": [],
    "array_tags": [
      "digital",
      "date",
      "distance",
      "heartrate",
      "days",
      "calories",
      "battery",
      "steps",
      "czech"
    ],
    "list_album": [
      {
        "id_album": "2433880",
        "link_thumb": "https://live.staticflickr.com/65535/51672428715_5b362ecd27_o.gif",
        "title": "None"
      }
    ]
  }
]